{
    "initialize_model" : "initialize_model",
    "load_weights" : "load_weights",
    "load_checkpoint" : "load_checkpoint",
    "model_load_state_dict" : "model_load_state_dict",
    "model_quantization" : "model_quantization",
    "quantize_based_on_type" : "quantize_based_on_type_custom_int8_ll_wt",
    "move_model_to_cuda" : "move_model_to_cuda",
    "text_completion" : "text_completion",
    "transformer" : "Transformer",
    "token_embedding" : "tok_embeddings: ParallelEmbedding",
    "transformer_block" : "0: TransformerBlock",
    "attention_norm" : "attention_norm: RMSNorm",
    "attention" : "attention: Attention",
    "wq" : "wq: QuantizedInt8LinearLayer",
    "wk" : "wk: QuantizedInt8LinearLayer",
    "wv" : "wv: QuantizedInt8LinearLayer",
    "wo" : "wo: QuantizedInt8LinearLayer",
    "feed_forward" : "feed_forward: FeedForward",
    "w1" : "w1: QuantizedInt8LinearLayer",
    "w2" : "w2: QuantizedInt8LinearLayer",
    "w3" : "w3: QuantizedInt8LinearLayer",
    "ffn_norm" : "ffn_norm: RMSNorm",
    "output" : "output: QuantizedInt8LinearLayer"
}